{
 "ANIMAL": [
  "r\u0101poka",
  "kutupapa",
  "kaio",
  "k\u014dheriheri",
  "h\u014diho_tar\u0101whe",
  "kewa",
  "pepeketua",
  "whakahao",
  "kirera",
  "maroro",
  "k\u014dkako",
  "k\u0101hu",
  "w\u0101pi",
  "mane",
  "p\u012b_kaimahi",
  "ihu_koropuku",
  "piwara",
  "makipai",
  "pakaka",
  "mang\u014d_pounamu",
  "k\u0101kahi",
  "kioretai",
  "kararehe_wh\u0101ngote",
  "mang\u014d_tuatini",
  "ngaro_w\u012bw\u012b",
  "k\u014dheru",
  "p\u012bwa",
  "k\u014dtoretore",
  "taha_pounamu",
  "mang\u014d_au_pounamu",
  "m\u016bheke",
  "p\u016bkeko",
  "taiwharu",
  "h\u016bmenga",
  "pakake",
  "p\u016bp\u016b_tarakihi",
  "k\u016b\u012b",
  "peketua",
  "pea_huka",
  "whai_repo",
  "kokoroihe",
  "k\u0101unga",
  "t\u016bpoupou",
  "kur\u012b_whakangau",
  "karoro",
  "takahikare",
  "paikea",
  "aupounamu",
  "rauwheke",
  "hinamoki",
  "heroni",
  "p\u012b_huauri",
  "p\u0101titotito",
  "mang\u014d_ururoa",
  "k\u014dputaputa",
  "moko_ngata",
  "waewae_m\u0101totoru",
  "kahuku"
 ],
 "ORG": [
  "haukaiwahine",
  "te_k\u016brae_matomato",
  "r\u0101ngai_puoro_tuatini",
  "r\u014dp\u016b_arop\u0101",
  "taka_puoro",
  "mautohetanga",
  "karap\u012bpiti",
  "tau\u0101_moana",
  "andorra_la_vella",
  "akunga",
  "iwi_f\u0101'\u016btaha",
  "r\u014dp\u016b_t\u014drangap\u016b",
  "whakangaio",
  "iwi_wh\u0101nui",
  "hunga_mahi",
  "wai_m\u0101ori",
  "ko_ahau",
  "ko_taku_ingoa",
  "pia_ngaungau",
  "p\u0101tariana",
  "k\u014dti_mana_nui",
  "riaka",
  "pou_t\u0101whirowhiro",
  "pito_ki_te_tonga",
  "\u0101tetenga",
  "whare_whakapakari",
  "p\u016b_kotahi",
  "whare_korikori",
  "akoranga_matauranga",
  "tau\u0101_rangi",
  "epa",
  "rohe_p\u014dti",
  "ai",
  "te_mea_ai",
  "oni",
  "tauhokohoko",
  "k\u014dp\u016b",
  "huinga_raraunga",
  "h\u0101hi_whakaminenga",
  "pito_tonga",
  "p\u014dhutuhutu",
  "whare_o_runga",
  "kini_ekuatoria",
  "t\u0101wera",
  "kawhe_m\u014dwai",
  "purini_huar\u0101kau",
  "tohu_p\u0101tai",
  "h\u0101hi_weteriana",
  "k\u0101wanatanga",
  "kaunihera_motuhake_a_te_k\u012bngi",
  "r\u014dp\u016b_awheawhe",
  "whare_whakapakari_tinana",
  "moe_whakawhitiwhiti"
 ],
 "FOOD": [
  "aihikir\u012bmi",
  "kai_paramanawa",
  "k\u014dk\u014d",
  "kanokawhe",
  "towhiro",
  "pia_ngaungau",
  "k\u016bmamatanga",
  "puehu_huka",
  "tinipia",
  "miraka_kore_kir\u012bmi",
  "purini",
  "kir\u012bmi_t\u0101whiuwhiu",
  "wai_r\u0113mana",
  "kohia",
  "wai_inu",
  "paura_k\u014dk\u014d",
  "wai_reka",
  "kir\u012bmi_p\u0101hukahuka",
  "parakuihi",
  "hamapaka",
  "akakaik\u016b",
  "purini_huar\u0101kau",
  "p\u012brere",
  "keke_m\u0101renatanga",
  "kawhe"
 ],
 "PLANT": [
  "p\u012bni_nunui",
  "hangehange",
  "p\u0101t\u016b_p\u016btau",
  "p\u014dhuehue",
  "p\u014dhue",
  "maire_taiki",
  "p\u0101p\u0101henga",
  "t\u014dhuka",
  "remuroa",
  "aonan\u012b",
  "waiora",
  "horopito",
  "manarini",
  "pine",
  "r\u0101kau_whai_hua",
  "hengahenga",
  "r\u0101kau_niu",
  "kakau_moana",
  "k\u0101rikih\u0101ura",
  "erema",
  "aute",
  "natahama",
  "p\u0101kau",
  "puhikawa",
  "koko_o_te_pokohiwi",
  "taru_kawa",
  "hakeka",
  "p\u0101hengahenga",
  "hikamoa",
  "hikamora",
  "raupeti",
  "puatororaro",
  "p\u012bti",
  "puarangi",
  "tut\u0101huna",
  "taraonga",
  "wirou",
  "rewarewa",
  "manitareki",
  "parakipere",
  "horera",
  "t\u016btae_k\u0101hu",
  "paina",
  "karepar\u0101oa",
  "ringatoi",
  "t\u016btaek\u0101hu",
  "whangewhange",
  "p\u0101koukou",
  "k\u0101piti",
  "r\u0113tihi",
  "p\u012bti_whero"
 ],
 "JOB": [
  "kaiwhakangahau",
  "p\u012bhopa",
  "m\u0101hita_kura",
  "para",
  "kairaup\u012b",
  "kaimahi_k\u0101raho",
  "kaituhi",
  "toihau",
  "waha_k\u014drero",
  "kurutangi",
  "kaihaut\u016b",
  "papaunguungu",
  "mate",
  "\u0101piha",
  "kaiwhakatupu",
  "rehu_p\u0101keh\u0101",
  "kaihoko_whakamutunga",
  "takahoa",
  "toihuarewa",
  "k\u0101para_iti",
  "moremore",
  "kaitiaki",
  "kaiwhakaahua",
  "kaihanga",
  "kaik\u014dmihana",
  "kaiwhakahaere",
  "kai\u0101rai",
  "waetea",
  "r\u016btene",
  "kaimahi",
  "kait\u0101",
  "kaihanga_r\u012bhi",
  "taupua",
  "tauwh\u0101nui",
  "kiripaepae",
  "m\u0101tanga_h\u0101pai",
  "kaimotomoto",
  "kair\u0113hita",
  "kaituki",
  "rewher\u012b",
  "kaiwhakature",
  "kaih\u0101pai_\u014d",
  "kai\u0101rahi",
  "t\u0101kuta_niho",
  "\u0101tamira",
  "kaimatira",
  "meiha",
  "p\u016brere_horoi_maitai",
  "kaiwhakatangi",
  "kaikauhau",
  "menetia",
  "h\u014dia_eke_h\u014diho",
  "kaiwhakahau",
  "t\u0101kuta",
  "kaiwahakapurupuru",
  "m\u0101tanga_mate_hinengaro",
  "pekepoho",
  "kait\u0101tari",
  "h\u014dia_heketau",
  "k\u0101nara",
  "t\u0101t\u0101riki",
  "kaiw\u0113teri",
  "poumatua",
  "kaiwhawhai_ahi",
  "kaitaraiwa",
  "kaip\u0101nui",
  "kaiwhakatere",
  "kairaranga",
  "kaimahi_uku",
  "pirihimana",
  "kaiwhakapakoko",
  "kaiwhakaue",
  "kaiwhaihanga",
  "kaitaupaepae",
  "ihorei",
  "p\u016bkorero",
  "h\u0113kena",
  "kaiwhakam\u0101ori",
  "p\u016brere_horoi_k\u0101kahu",
  "meihana",
  "kaikutikuti",
  "kaiwhatu",
  "perehitini",
  "haihana_karauna",
  "amapaea",
  "tuari_mahi_kawhe",
  "kait\u0101tari_kaute",
  "kaihaeana_h\u014diho",
  "kaiwhakahaere_matua",
  "pouako",
  "kaikatik\u012bhama",
  "kaitakitaki",
  "kaituhi_pakiwaituhi",
  "ihu_oneone",
  "kaipakihi",
  "katekita",
  "arahi",
  "haut\u016b",
  "kaihoahoa",
  "kaihoroi",
  "kuruwhengi",
  "kaiaka_m\u012bhini",
  "wh\u0101rangi",
  "h\u0113para",
  "wahine_whakawhanau",
  "h\u0113ramana",
  "manukura",
  "kaiwhakatau_manuhiri",
  "kaiwhakairo",
  "kaitiki",
  "aporei",
  "kait\u016bao",
  "kaipatopato",
  "reo_k\u014drero",
  "matawh\u0101nui",
  "kair\u016bri_whenua",
  "mea_whakatangi",
  "kaitiaki_r\u0101kau",
  "kaiwhakataki",
  "kairapu",
  "kaiwaihanga",
  "kaiwhiringa_reo",
  "kaiwhaowhao",
  "kait\u0101wai",
  "meihi",
  "karere",
  "kaiamo_m\u0113ra",
  "kaihanga_ture",
  "m\u0101tanga_kai",
  "whakatoke",
  "takawaenga",
  "r\u014dia",
  "kaimataara",
  "p\u016brere_horoi_r\u012bhi",
  "k\u0101tipa",
  "kaimahi_m\u0101ra",
  "kaiwhakawhanau",
  "t\u0101kuta_poka",
  "p\u0101raeroa",
  "kaiwhakat\u016b",
  "minita",
  "kaiper\u0113hi",
  "m\u012bhini_horoi_r\u012bhi",
  "kaim\u0101tai_hauropi",
  "h\u014dia",
  "kaiwhakaako",
  "kairangaranga",
  "kaitia",
  "kaipatu_tohor\u0101",
  "kaiwhakakata",
  "kaikuti_makawe",
  "kaiwhakapuru",
  "hokomirimiri",
  "pirikitia",
  "kait\u0101taki",
  "k\u0101pene",
  "heamana",
  "kaupoai",
  "poutoko",
  "kaihokohoko",
  "kaiwhakaputa",
  "kair\u016bri",
  "kaikauwhau",
  "ahorangi",
  "kaikohi_t\u0101ke",
  "w\u0101tene",
  "kaiomaoma",
  "t\u016bmataiti",
  "ariki_whawhai",
  "kaumoana",
  "waewae_kai_pakiaka",
  "kaitaki",
  "kait\u0101rai",
  "kaiwhakanoho_reta",
  "kaitereina",
  "te_rua",
  "kaitakawaenga",
  "kaiwea",
  "kaing\u0101rahu",
  "kaip\u016btaiao",
  "haihana",
  "kaik\u014drero",
  "t\u0101maramara",
  "kaihautu",
  "m\u0101tanga_p\u016btaiao",
  "m\u014dkai_taurekareka",
  "kaiamo",
  "kahunga",
  "kaiwhakahua",
  "kaitangowhakaahua",
  "kauhoe",
  "kaiurungi",
  "kaiwaewae",
  "monita"
 ],
 "PRODUCT": [
  "pakanga_tuatahi_o_te_ao",
  "waiata_a_horomona",
  "puka_w\u0101hitau",
  "kawenata_hou",
  "wh\u0101nau_poka",
  "kanohi_k\u0101hu",
  "waka_k\u014dpiko_tuarangi",
  "niu_tireni",
  "kani_\u0101nau",
  "piharoa",
  "hana_k\u014dk\u014d",
  "ahutoru",
  "inoi_a_te_ariki",
  "t\u016btutupo",
  "kuki_airani",
  "ata_m\u0101rie",
  "taupuni_\u0101tea",
  "wh\u0101nautanga_poka",
  "piritini_nui",
  "aotearoa",
  "wh\u0101nau_m\u0101rama",
  "pakanga_tuarua_o_te_ao",
  "mea_whakatangitangi"
 ],
 "PUBLIC_FIGURE": [
  "h\u0113ri",
  "k\u0101napera",
  "riria",
  "kiripeta",
  "meri_makarini",
  "t\u0101mati",
  "ihu_karaiti",
  "manawa_ora",
  "kerekori",
  "kauhoe",
  "anatoni",
  "kataraina",
  "h\u014dri",
  "r\u014dpata",
  "t\u016bmanako",
  "taituha",
  "eruera",
  "irih\u0101peti",
  "r\u0113nata",
  "anahera_kaitiaki",
  "r\u0101pata",
  "one",
  "kauranga",
  "reo_pekerangi",
  "i",
  "a",
  "h\u0113nare",
  "k\u0101tarina"
 ],
 "DISEASE": [
  "mamamama",
  "poutukitanga",
  "hinamokimoki",
  "turiwaitaitai",
  "koeketanga",
  "kinawhea",
  "para",
  "kawekawenga",
  "katirehe",
  "kikikiki",
  "kaimatatanga",
  "moremore",
  "taratarawai",
  "maiorohea",
  "kaik\u014diwi",
  "huang\u014d",
  "kaikoiwi",
  "kaihanu",
  "kaiwhakat\u016b",
  "tokopuhake",
  "tongako",
  "pukoko",
  "taukini",
  "pukuwhenewhene",
  "mono",
  "kotiuru",
  "hikahikanga",
  "paipairuaki",
  "mania",
  "ki",
  "wharatanga",
  "korera",
  "kaitoroh\u012btanga",
  "h\u014dripiripi",
  "rewharewha",
  "papahewa",
  "mamae",
  "kokohu",
  "marupo",
  "karawaka",
  "moe_takarerewa",
  "kuru",
  "kaikaru",
  "mariao",
  "tia",
  "kukunetanga",
  "k\u014dea"
 ],
 "LOCATION": [
  "hana_k\u014dk\u014d",
  "tau_hou_hari",
  "me_kore",
  "te_hononga_o_amerika",
  "roiata",
  "wai_m\u0101ori",
  "te_ika_a_m\u0101ui",
  "tapepetanga",
  "\u014dwhanga",
  "te_waipounamu",
  "e_pai_ana",
  "whare_h\u0101kinakina",
  "whare_hiko",
  "meri_makarini",
  "tau\u0101_rangi",
  "h\u012braka",
  "papa_purei_t\u0113nehi",
  "koki_h\u0101ngai",
  "te_k\u016brae_matomato",
  "ng\u0101_whenua_t\u014dp\u016b_o_amerika",
  "amerika",
  "te_ikaroa",
  "p\u016b_ngahunga",
  "tautoru",
  "hononga_o_amerika",
  "te_taki_o_autahi",
  "te_moana_nui_a_kiwa",
  "t\u0101one_nui",
  "papa_t\u0101karo",
  "te_mang\u014droa"
 ],
 "GENDER": [
  "uha",
  "kouwha",
  "taitam\u0101hine",
  "k\u014dhine",
  "taitama",
  "k\u014dtiro",
  "t\u0101hake",
  "titupu",
  "purengi",
  "k\u014dhaia",
  "uwha"
 ],
 "PERSON_PRONOUN": [
  "\u014d_m\u0101tau",
  "me",
  "t\u0101ku",
  "n\u0101haku",
  "n\u0101ku",
  "\u0101_m\u0101tau",
  "\u014dna",
  "t\u0101_t\u0101ua",
  "m\u0101tau_m\u0101tou",
  "t\u0101_m\u0101tau",
  "\u0101na",
  "t\u0101u",
  "t\u014d_m\u0101ua",
  "m\u0101tou",
  "\u014du",
  "\u014dku",
  "koutou",
  "m\u0101ua",
  "\u0101_t\u0101tau",
  "t\u014d_m\u0101tau",
  "k\u014drua",
  "t\u014dku",
  "t\u0101_m\u0101ua",
  "n\u014dhoku",
  "\u0101u",
  "t\u0101tau_t\u0101tou",
  "keringa",
  "t\u014dna",
  "\u014d_m\u0101ua",
  "t\u0101ua",
  "n\u014dku",
  "t\u0101na",
  "t\u014du",
  "i",
  "\u0101ku",
  "t\u014d_t\u0101ua",
  "\u014d_t\u0101tau"
 ],
 "RACE": [
  "\u0101rapi",
  "mangumangu"
 ],
 "LANGUAGE": [
  "kariki",
  "p\u014dtik\u012b",
  "uwha_hipi",
  "ingarihi",
  "r\u0101tini",
  "itariana",
  "komi",
  "p\u0101niora",
  "reo_w\u012bw\u012b",
  "k\u0101tua_hipi",
  "ewe",
  "nauru"
 ],
 "BIO_CHEM_ENTITY": [
  "konutea_p\u0101kawa_waro",
  "waikawa_wai\u016b",
  "takawai_h\u0101orarua",
  "haukini_p\u0101kawaota",
  "waikawa_ngako",
  "mate_ohorere"
 ],
 "SOC_ECO_CLASS": [
  "tokoitiiti",
  "okotahi",
  "ouou",
  "te_aitanga_a_tiki",
  "hunga_pakipaki",
  "k\u014dtahitahi",
  "porihanga",
  "wahinetanga",
  "toru_toru",
  "itiiti",
  "tokoiti",
  "k\u0101hui_ariki",
  "whakarangatiratanga"
 ],
 "QUANTITY": [
  "ine_t\u016bnga_waka",
  "tau_maha",
  "t\u0101ra",
  "tauwehe_whakahau",
  "matirua",
  "kotiri",
  "rua_ngahuru_m\u0101_tahi",
  "p\u016btake_toru",
  "t\u016bnga_waka",
  "rup\u012b",
  "tau_iraoho",
  "kanohi_ki_te_kanohi",
  "tau_kewha",
  "rua_tekau_m\u0101_tahi",
  "tauwehe_toit\u016b",
  "rae_ki_te_rae",
  "p\u016btake_run",
  "tau_toit\u016b",
  "tau_tatau",
  "tau_t\u016bturu",
  "rupi",
  "tone",
  "tau_karihi",
  "heringi",
  "p\u0101tukituki",
  "h\u0101roto",
  "ahutoru"
 ],
 "DATE": [
  "marama_hua",
  "w\u0101heke",
  "koroheketanga",
  "tau_kuhurangi",
  "tau_p\u016btea",
  "\u0101tahir\u0101",
  "r\u0101kaunui",
  "te_ihu_o_hinetakurua",
  "tauinew\u0101",
  "te_ihu_o_hineraumati"
 ],
 "LAW": [
  "k\u014dti_mana_nui",
  "r\u014dia_matua"
 ],
 "RELIGION_MEMBER": [
  "mihinare",
  "kaiiriiri",
  "\u0101potoro",
  "porotehana",
  "w\u0113teriana",
  "perehipitiriana"
 ],
 "PERSON": [
  "ihu_noke",
  "te_rangi"
 ],
 "GPE": [
  "kawenata_hou",
  "te_tai_rei"
 ],
 "FAC": [
  "whare_r\u012bhi",
  "terenga",
  "piriti_whakat\u0101rewa",
  "mataihi",
  "whare_pirihimana",
  "wharehokohoko"
 ],
 "POLITICAL_PARTY": [
  "mautohetanga",
  "r\u014dp\u016b_t\u014drangap\u016b",
  "\u0101tetenga"
 ],
 "POLITICAL_PARTY_MEMBER": [
  "whiwhingatahi"
 ],
 "ANAT": [
  "kikopuku",
  "tangai_kak\u012b"
 ],
 "MEDICAL_THERAPY": [
  "p\u0113hanga_toto"
 ],
 "EVENT": [
  "peke_t\u012btoko"
 ],
 "FIRST_NAME_MALE": [],
 "LAST_NAME_MALE": [],
 "FIRST_NAME_FEMALE": [],
 "LAST_NAME_FEMALE": [],
 "FIRST_NAME": [],
 "LAST_NAME": [],
 "SUFIX_MALE": [],
 "SUFIX_FEMALE": [],
 "binary_gender_swap": {
  "tutahe": "tiuka",
  "tamahine": "purengi",
  "uwha": "t\u0101ne",
  "kouwha": "t\u0101ne",
  "wahine": "t\u0101ne",
  "uha": "t\u0101ne",
  "k\u014dhine": "purengi",
  "hine": "purengi",
  "taitam\u0101hine": "purengi",
  "k\u014dtiro": "purengi",
  "k\u014dhaia": "purengi",
  "t\u014dna": "\u0101na",
  "\u0101na": "t\u014dna",
  "k\u0101na": "\u0101na",
  "t\u0101na": "\u014dna",
  "\u014dna": "k\u0101na",
  "pirinihi": "wheao",
  "kuini": "kingi",
  "tuakana": "uka",
  "tuahine": "taina",
  "teina": "taina",
  "marokore": "t\u0101ne_takakau",
  "takakau": "t\u0101ne_takakau",
  "maro_kau": "t\u0101ne_takakau",
  "wahine_kiritapu": "takakau",
  "wahine_takakau": "t\u0101ne_takakau",
  "wahine_taumaro": "t\u0101ne_takakau",
  "tam\u0101hine_k\u0113": "tamat\u0101ne_whakaangi",
  "hine_whakaangi": "tamat\u0101ne_whakaangi",
  "tam\u0101hine_whakaangi": "tamat\u0101ne_whakaangi",
  "whaea_k\u0113": "matua_whakaangi",
  "whaea_whakaangi": "matua_whakaangi",
  "takahore": "pouaru",
  "pouaru": "takahore",
  "hoa_rangatira": "t\u0101ne",
  "hoa_wahine": "hoa_t\u0101ne",
  "tamaiti_t\u0101ne": "k\u014dhaia",
  "taitama": "hine"
 },
 "other_gender_swap": {
  "one": "hona",
  "r\u0101ua": "hona",
  "r\u0101tau": "\u0101na",
  "r\u0101tou": "hona",
  "t\u014d_r\u0101ua": "\u014dna",
  "\u0101_r\u0101ua": "t\u0101na",
  "\u014d_r\u0101ua": "\u014dna",
  "\u0101_r\u0101tau": "t\u014dna",
  "\u014d_r\u0101tau": "k\u0101na",
  "t\u0101_r\u0101tau": "t\u014dna",
  "t\u014d_r\u0101tau": "\u014dna",
  "t\u0101_r\u0101ua": "\u0101na",
  "wao": "hona",
  "hona": "one",
  "t\u014dna": "t\u0101_r\u0101ua",
  "\u0101na": "\u014d_r\u0101ua",
  "k\u0101na": "\u014d_r\u0101ua",
  "t\u0101na": "\u0101_r\u0101tau",
  "\u014dna": "\u0101_r\u0101ua"
 },
 "en_pronoun2gender": {
  "he": [
   "t\u0101ne",
   "taitama",
   "korok\u0113",
   "purengi",
   "tamaiti_t\u0101ne",
   "t\u0101hake",
   "titupu"
  ],
  "she": [
   "tuakana",
   "tohipa",
   "hine",
   "kouwha",
   "uha",
   "uwha",
   "k\u014dhaia",
   "hauare",
   "taitam\u0101hine",
   "tamahine",
   "k\u014dhine",
   "wahine",
   "tuahine",
   "k\u014dtiro",
   "kahurangi",
   "hihipa"
  ]
 },
 "en_pronoun2pronoun": {
  "he": [
   "k\u0101na",
   "t\u0101na",
   "\u014dna",
   "t\u014dna",
   "\u0101na"
  ],
  "she": [
   "k\u0101na",
   "t\u0101na",
   "hona",
   "\u014dna",
   "t\u014dna",
   "\u0101na"
  ],
  "they": [
   "\u014d_r\u0101tau",
   "r\u0101tau",
   "t\u014d_r\u0101ua",
   "r\u0101tou",
   "r\u0101ua",
   "wao",
   "one",
   "\u0101_r\u0101tau",
   "\u0101_r\u0101ua",
   "\u014d_r\u0101ua",
   "t\u0101_r\u0101tau",
   "t\u014d_r\u0101tau",
   "t\u0101_r\u0101ua"
  ],
  "it": [
   "k\u0101na",
   "\u0113nei",
   "t\u0113nei"
  ]
 },
 "en_pronoun2title": {},
 "PREFIX_MALE": [],
 "PREFIX_FEMALE": [],
 "person2religion": {}
}